wallapopUpdateWatcher/__init__.py
wallapopUpdateWatcher/producto.py
wallapopUpdateWatcher/query.py
wallapopUpdateWatcher/strategies.py
wallapopUpdateWatcher/updateWatcher.py
wallapopupdatewatcher-0.1.3.dist-info/LICENSE
wallapopupdatewatcher-0.1.3.dist-info/METADATA
wallapopupdatewatcher-0.1.3.dist-info/WHEEL
wallapopupdatewatcher-0.1.3.dist-info/RECORD
