Metadata-Version: 2.1
Name: wallapopupdatewatcher
Version: 0.1.3
Summary: A library to watch for new items at wallapop.es
Home-page: https://github.com/Adair-GA/wallapopUpdateWatcher
License: GNU General Public License v3 (GPLv3)
Author: Adair-GA
Author-email: adairyves@gmail.com
Requires-Python: >=3.7,<4.0
Classifier: Development Status :: 4 - Beta
Classifier: Intended Audience :: Developers
Classifier: License :: OSI Approved :: GNU General Public License v3 (GPLv3)
Classifier: License :: Other/Proprietary License
Classifier: Programming Language :: Python :: 3
Classifier: Programming Language :: Python :: 3.7
Classifier: Programming Language :: Python :: 3.8
Classifier: Programming Language :: Python :: 3.9
Classifier: Programming Language :: Python :: 3.10
Classifier: Programming Language :: Python :: 3.11
Classifier: Programming Language :: Python :: 3.11
Classifier: Topic :: Software Development
Requires-Dist: httpx (>=0.23.3,<0.24.0)
Project-URL: Repository, https://github.com/Adair-GA/wallapopUpdateWatcher
